prefect_northflank/__init__.py
prefect_northflank/client.py
prefect_northflank/credentials.py
prefect_northflank/schemas.py
prefect_northflank/worker.py
prefect_northflank-0.2.0.dist-info/METADATA
prefect_northflank-0.2.0.dist-info/WHEEL
prefect_northflank-0.2.0.dist-info/entry_points.txt
prefect_northflank-0.2.0.dist-info/RECORD
