Metadata-Version: 2.4
Name: prefect-northflank
Version: 0.2.0
Summary: Prefect integrations for Northflank platform
Author-email: Northflank <support@northflank.com>
Maintainer-email: Northflank <support@northflank.com>
License: Apache License 2.0
Keywords: containers,jobs,northflank,prefect
Requires-Python: >=3.12
Requires-Dist: httpx>=0.24.0
Requires-Dist: prefect>=3.1.1
Requires-Dist: pydantic>=2.0.0
